setup.py
zson/__init__.py
zson.egg-info/PKG-INFO
zson.egg-info/SOURCES.txt
zson.egg-info/dependency_links.txt
zson.egg-info/entry_points.txt
zson.egg-info/requires.txt
zson.egg-info/top_level.txt