Metadata-Version: 1.0
Name: zson
Version: 1.0.17
Summary: A JSON serializer for Kombu (and therefore also Celery) that supports encoding objects by defining to_json and from_json methods.
Home-page: UNKNOWN
Author: Zakir Durumeric
Author-email: zakird@gmail.com
License: Apache License, Version 2.0
Keywords: python kombu celery json
Platform: UNKNOWN
